{"schema":"pipedata-component-aliases/v1","phase":"DB_PHASE_50","mode":"EXACT_ALIAS_ONLY","rows":[{"canonical":"VALVE","aliases":["VLV","VALVES"]},{"canonical":"GATE","aliases":["GATE VALVE","VLV1"]},{"canonical":"FLANGE","aliases":["FLG","FLANGES"]},{"canonical":"WN","aliases":["WELD NECK","WELDING NECK","WNRF"]},{"canonical":"SO","aliases":["SLIP ON","SORF"]},{"canonical":"BLIND","aliases":["BLIND FLANGE","BLRF"]},{"canonical":"PIPE","aliases":["PIP","TUBE"]},{"canonical":"SCH40","aliases":["SCHEDULE 40","SCH 40","STD40"]},{"canonical":"SCH80","aliases":["SCHEDULE 80","SCH 80","XS"]},{"canonical":"FITTING","aliases":["FTBW","BUTTWELD FITTING"]},{"canonical":"ELBOW_90","aliases":["90 ELBOW","ELBOW 90","90 DEG ELBOW"]},{"canonical":"ELBOW_45","aliases":["45 ELBOW","ELBOW 45","45 DEG ELBOW"]},{"canonical":"GASKET","aliases":["GSK","GASKETS"]},{"canonical":"SUPPORT","aliases":["SUP","SHOE","GUIDE"]}]}